bit_chess/__init__.py
bit_chess/board.py
bit_chess-0.1.0.dist-info/LICENSE
bit_chess-0.1.0.dist-info/METADATA
bit_chess-0.1.0.dist-info/WHEEL
bit_chess-0.1.0.dist-info/top_level.txt
bit_chess-0.1.0.dist-info/RECORD
