Metadata-Version: 2.1
Name: bit-chess
Version: 0.1.0
Summary: Python package for chess
Home-page: https://github.com/pypa/bit-chess
Author: tpxHorus
Project-URL: Bug Tracker, https://github.com/pypa/bit-chess/issues
Classifier: Programming Language :: Python :: 3
Classifier: License :: OSI Approved :: MIT License
Classifier: Operating System :: OS Independent
Requires-Python: >=3.10
License-File: LICENSE
